jaccount_cli/__init__.py
jaccount_cli/ascii.py
jaccount_cli/asyncio.py
jaccount_cli-0.0.5.dist-info/LICENSE
jaccount_cli-0.0.5.dist-info/METADATA
jaccount_cli-0.0.5.dist-info/WHEEL
jaccount_cli-0.0.5.dist-info/top_level.txt
jaccount_cli-0.0.5.dist-info/RECORD
