Metadata-Version: 2.1
Name: jaccount-cli
Version: 0.0.5
Summary: A small plugin to help use jaccount login in cli programs.
Home-page: https://github.com/tc-imba/python-jaccount-cli
Author: tc-imba
Author-email: liuyh615@126.com
Maintainer: tc-imba
Maintainer-email: liuyh615@126.com
License: MIT
Project-URL: Bug Reports, https://github.com/tc-imba/python-jaccount-cli/issues
Project-URL: Source, https://github.com/tc-imba/python-jaccount-cli
Platform: UNKNOWN
License-File: LICENSE
Requires-Dist: aiohttp
Requires-Dist: beautifulsoup4
Requires-Dist: pillow
